vsfieldkit/__init__.py
vsfieldkit/deinterlacing.py
vsfieldkit/interlacing.py
vsfieldkit/kernels.py
vsfieldkit/output.py
vsfieldkit/py.typed
vsfieldkit/repair.py
vsfieldkit/scanning.py
vsfieldkit/types.py
vsfieldkit/util.py
vsfieldkit/vapoursynth.py
vsfieldkit-2.1.0.dist-info/LICENSE.txt
vsfieldkit-2.1.0.dist-info/METADATA
vsfieldkit-2.1.0.dist-info/WHEEL
vsfieldkit-2.1.0.dist-info/top_level.txt
vsfieldkit-2.1.0.dist-info/RECORD
