Metadata-Version: 2.1
Name: vsfieldkit
Version: 2.1.0
Home-page: https://github.com/JustinTArthur/vsfieldkit
Author: Justin Turner Arthur
Author-email: justinarthur@gmail.com
License: MIT
Classifier: License :: OSI Approved :: MIT License
Classifier: Topic :: Multimedia :: Video
Classifier: Topic :: Multimedia :: Video :: Conversion
Classifier: Topic :: Software Development :: Libraries
Classifier: Topic :: Software Development :: Libraries :: Python Modules
Classifier: Typing :: Typed
Requires-Python: >=3.6
License-File: LICENSE.txt
